DMM_PyTorch/DMM.py
DMM_PyTorch/__init__.py
DMM_PyTorch-0.1.2.dist-info/LICENSE
DMM_PyTorch-0.1.2.dist-info/METADATA
DMM_PyTorch-0.1.2.dist-info/WHEEL
DMM_PyTorch-0.1.2.dist-info/top_level.txt
DMM_PyTorch-0.1.2.dist-info/RECORD
