Metadata-Version: 2.1
Name: DMM-PyTorch
Version: 0.1.2
Summary: Debiased Mapping for Full-Reference Image Quality Assessment
Home-page: https://github.com/Baoliang93/DMM
Author: Baoliang CHEN
Author-email: blchen@scnu.edu.cn
License: MIT
Keywords: pytorch,Quality,Debiased,Full-reference,metric
Platform: python
License-File: LICENSE
Requires-Dist: torch (>=1.0)
